{
    "title": "number of user accesses",
    "visState": "{\"type\":\"line\",\"params\":{\"addLegend\":true,\"addTimeMarker\":false,\"addTooltip\":true,\"defaultYExtents\":false,\"drawLinesBetweenPoints\":true,\"interpolate\":\"linear\",\"radiusRatio\":9,\"scale\":\"linear\",\"setYExtents\":false,\"shareYAxis\":true,\"showCircles\":true,\"smoothLines\":false,\"times\":[],\"yAxis\":{}},\"aggs\":[{\"id\":\"1\",\"type\":\"count\",\"schema\":\"metric\",\"params\":{}},{\"id\":\"2\",\"type\":\"date_histogram\",\"schema\":\"segment\",\"params\":{\"field\":\"TIMESTAMP\",\"interval\":\"d\",\"customInterval\":\"2h\",\"min_doc_count\":1,\"extended_bounds\":{}}}],\"listeners\":{}}",
    "uiStateJSON": "{}",
    "description": "",
    "version": 1,
    "kibanaSavedObjectMeta": {
        "searchSourceJSON": "{\"index\":\"auditingevents-*\",\"query\":{\"query_string\":{\"analyze_wildcard\":true,\"query\":\"ACTION:\\\"Access\\\"\"}},\"filter\":[]}"
    }
}
