{
    "title": "Show all created Resources/Services/Products",
    "visState": "{\"type\":\"line\",\"params\":{\"shareYAxis\":true,\"addTooltip\":true,\"addLegend\":true,\"showCircles\":true,\"smoothLines\":false,\"interpolate\":\"linear\",\"scale\":\"linear\",\"drawLinesBetweenPoints\":true,\"radiusRatio\":9,\"times\":[],\"addTimeMarker\":false,\"defaultYExtents\":false,\"setYExtents\":false,\"yAxis\":{}},\"aggs\":[{\"id\":\"1\",\"type\":\"count\",\"schema\":\"metric\",\"params\":{}},{\"id\":\"2\",\"type\":\"date_histogram\",\"schema\":\"segment\",\"params\":{\"field\":\"TIMESTAMP\",\"interval\":\"d\",\"customInterval\":\"2h\",\"min_doc_count\":1,\"extended_bounds\":{}}},{\"id\":\"3\",\"type\":\"terms\",\"schema\":\"group\",\"params\":{\"field\":\"RESOURCE_TYPE\",\"size\":5,\"order\":\"desc\",\"orderBy\":\"1\"}}],\"listeners\":{}}",
    "uiStateJSON": "{}",
    "description": "",
    "version": 1,
    "kibanaSavedObjectMeta": {
        "searchSourceJSON": "{\"index\":\"auditingevents-*\",\"query\":{\"query_string\":{\"query\":\"ACTION:\\\"Create\\\"\",\"analyze_wildcard\":true}},\"filter\":[]}"
    }
}
